{
    "meta": {
        "reg_no": "新北府教幼字字第1041548680土城0069之2號",
        "reg_docno": "六八北府教二字第68043468號",
        "reg_date": "1979\/03\/14",
        "title": "新北市私立立仁幼兒園",
        "owner": "黃愛珠",
        "city": "新北市",
        "town": "土城區",
        "type": "私立",
        "address": "[236]樂利街5號1、2樓",
        "floor": "1樓至2樓",
        "size": "592.94平方公尺",
        "size_in": "232平方公尺",
        "size_out": "360.94平方公尺",
        "tel": "(02)22613248",
        "url": "",
        "count_approved": "120",
        "shuttle": "",
        "pre_public": "無",
        "is_free5": "",
        "is_after": "無",
        "penalty": "無",
        "has_slip": "no"
    },
    "slip": {
        "5": {
            "上學期": {
                "months": "6",
                "class": {
                    "半日班": {
                        "學費": {
                            "收費期間": "學期",
                            "單價": "",
                            "小計": ""
                        },
                        "雜費": {
                            "收費期間": "月",
                            "單價": "",
                            "小計": ""
                        },
                        "材料費": {
                            "收費期間": "月",
                            "單價": "",
                            "小計": ""
                        },
                        "活動費": {
                            "收費期間": "月",
                            "單價": "",
                            "小計": ""
                        },
                        "午餐費": {
                            "收費期間": "月",
                            "單價": "",
                            "小計": ""
                        },
                        "點心費": {
                            "收費期間": "月",
                            "單價": "",
                            "小計": ""
                        },
                        "全學期總收費": {
                            "收費期間": "學期",
                            "單價": "",
                            "小計": ""
                        },
                        "交通費": {
                            "收費期間": "",
                            "單價": "",
                            "小計": ""
                        },
                        "課後延托費": {
                            "收費期間": "月",
                            "單價": "",
                            "小計": ""
                        },
                        "家長會費": {
                            "收費期間": "",
                            "單價": "",
                            "小計": ""
                        }
                    },
                    "全日班": {
                        "學費": {
                            "收費期間": "學期",
                            "單價": "15000",
                            "小計": "15000"
                        },
                        "雜費": {
                            "收費期間": "月",
                            "單價": "2861",
                            "小計": "17166"
                        },
                        "材料費": {
                            "收費期間": "月",
                            "單價": "900",
                            "小計": "5400"
                        },
                        "活動費": {
                            "收費期間": "月",
                            "單價": "1500",
                            "小計": "9000"
                        },
                        "午餐費": {
                            "收費期間": "月",
                            "單價": "1600",
                            "小計": "9600"
                        },
                        "點心費": {
                            "收費期間": "月",
                            "單價": "1139",
                            "小計": "6834"
                        },
                        "全學期總收費": {
                            "收費期間": "學期",
                            "單價": "63000",
                            "小計": "63000"
                        },
                        "交通費": {
                            "收費期間": "",
                            "單價": "",
                            "小計": ""
                        },
                        "課後延托費": {
                            "收費期間": "月",
                            "單價": "1575",
                            "小計": "9450"
                        },
                        "家長會費": {
                            "收費期間": "",
                            "單價": "",
                            "小計": ""
                        }
                    }
                }
            },
            "下學期": {
                "months": "6",
                "class": {
                    "半日班": {
                        "學費": {
                            "收費期間": "學期",
                            "單價": "",
                            "小計": ""
                        },
                        "雜費": {
                            "收費期間": "月",
                            "單價": "",
                            "小計": ""
                        },
                        "材料費": {
                            "收費期間": "月",
                            "單價": "",
                            "小計": ""
                        },
                        "活動費": {
                            "收費期間": "月",
                            "單價": "",
                            "小計": ""
                        },
                        "午餐費": {
                            "收費期間": "月",
                            "單價": "",
                            "小計": ""
                        },
                        "點心費": {
                            "收費期間": "月",
                            "單價": "",
                            "小計": ""
                        },
                        "全學期總收費": {
                            "收費期間": "學期",
                            "單價": "",
                            "小計": ""
                        },
                        "交通費": {
                            "收費期間": "",
                            "單價": "",
                            "小計": ""
                        },
                        "課後延托費": {
                            "收費期間": "月",
                            "單價": "",
                            "小計": ""
                        },
                        "家長會費": {
                            "收費期間": "",
                            "單價": "",
                            "小計": ""
                        }
                    },
                    "全日班": {
                        "學費": {
                            "收費期間": "學期",
                            "單價": "15000",
                            "小計": "15000"
                        },
                        "雜費": {
                            "收費期間": "月",
                            "單價": "2861",
                            "小計": "17166"
                        },
                        "材料費": {
                            "收費期間": "月",
                            "單價": "900",
                            "小計": "5400"
                        },
                        "活動費": {
                            "收費期間": "月",
                            "單價": "1500",
                            "小計": "9000"
                        },
                        "午餐費": {
                            "收費期間": "月",
                            "單價": "1600",
                            "小計": "9600"
                        },
                        "點心費": {
                            "收費期間": "月",
                            "單價": "1139",
                            "小計": "6834"
                        },
                        "全學期總收費": {
                            "收費期間": "學期",
                            "單價": "63000",
                            "小計": "63000"
                        },
                        "交通費": {
                            "收費期間": "",
                            "單價": "",
                            "小計": ""
                        },
                        "課後延托費": {
                            "收費期間": "月",
                            "單價": "1575",
                            "小計": "9450"
                        },
                        "家長會費": {
                            "收費期間": "",
                            "單價": "",
                            "小計": ""
                        }
                    }
                }
            }
        },
        "4": {
            "上學期": {
                "months": "6",
                "class": {
                    "半日班": {
                        "學費": {
                            "收費期間": "學期",
                            "單價": "",
                            "小計": ""
                        },
                        "雜費": {
                            "收費期間": "月",
                            "單價": "",
                            "小計": ""
                        },
                        "材料費": {
                            "收費期間": "月",
                            "單價": "",
                            "小計": ""
                        },
                        "活動費": {
                            "收費期間": "月",
                            "單價": "",
                            "小計": ""
                        },
                        "午餐費": {
                            "收費期間": "月",
                            "單價": "",
                            "小計": ""
                        },
                        "點心費": {
                            "收費期間": "月",
                            "單價": "",
                            "小計": ""
                        },
                        "全學期總收費": {
                            "收費期間": "學期",
                            "單價": "",
                            "小計": ""
                        },
                        "交通費": {
                            "收費期間": "",
                            "單價": "",
                            "小計": ""
                        },
                        "課後延托費": {
                            "收費期間": "月",
                            "單價": "",
                            "小計": ""
                        },
                        "家長會費": {
                            "收費期間": "",
                            "單價": "",
                            "小計": ""
                        }
                    },
                    "全日班": {
                        "學費": {
                            "收費期間": "學期",
                            "單價": "22800",
                            "小計": "22800"
                        },
                        "雜費": {
                            "收費期間": "月",
                            "單價": "3000",
                            "小計": "18000"
                        },
                        "材料費": {
                            "收費期間": "月",
                            "單價": "850",
                            "小計": "5100"
                        },
                        "活動費": {
                            "收費期間": "月",
                            "單價": "1100",
                            "小計": "6600"
                        },
                        "午餐費": {
                            "收費期間": "月",
                            "單價": "1760",
                            "小計": "10560"
                        },
                        "點心費": {
                            "收費期間": "月",
                            "單價": "1540",
                            "小計": "9240"
                        },
                        "全學期總收費": {
                            "收費期間": "學期",
                            "單價": "72300",
                            "小計": "72300"
                        },
                        "交通費": {
                            "收費期間": "",
                            "單價": "",
                            "小計": ""
                        },
                        "課後延托費": {
                            "收費期間": "月",
                            "單價": "2500",
                            "小計": "15000"
                        },
                        "家長會費": {
                            "收費期間": "",
                            "單價": "",
                            "小計": ""
                        }
                    }
                }
            },
            "下學期": {
                "months": "6",
                "class": {
                    "半日班": {
                        "學費": {
                            "收費期間": "學期",
                            "單價": "",
                            "小計": ""
                        },
                        "雜費": {
                            "收費期間": "月",
                            "單價": "",
                            "小計": ""
                        },
                        "材料費": {
                            "收費期間": "月",
                            "單價": "",
                            "小計": ""
                        },
                        "活動費": {
                            "收費期間": "月",
                            "單價": "",
                            "小計": ""
                        },
                        "午餐費": {
                            "收費期間": "月",
                            "單價": "",
                            "小計": ""
                        },
                        "點心費": {
                            "收費期間": "月",
                            "單價": "",
                            "小計": ""
                        },
                        "全學期總收費": {
                            "收費期間": "學期",
                            "單價": "",
                            "小計": ""
                        },
                        "交通費": {
                            "收費期間": "",
                            "單價": "",
                            "小計": ""
                        },
                        "課後延托費": {
                            "收費期間": "月",
                            "單價": "",
                            "小計": ""
                        },
                        "家長會費": {
                            "收費期間": "",
                            "單價": "",
                            "小計": ""
                        }
                    },
                    "全日班": {
                        "學費": {
                            "收費期間": "學期",
                            "單價": "22800",
                            "小計": "22800"
                        },
                        "雜費": {
                            "收費期間": "月",
                            "單價": "3000",
                            "小計": "18000"
                        },
                        "材料費": {
                            "收費期間": "月",
                            "單價": "850",
                            "小計": "5100"
                        },
                        "活動費": {
                            "收費期間": "月",
                            "單價": "1100",
                            "小計": "6600"
                        },
                        "午餐費": {
                            "收費期間": "月",
                            "單價": "1760",
                            "小計": "10560"
                        },
                        "點心費": {
                            "收費期間": "月",
                            "單價": "1540",
                            "小計": "9240"
                        },
                        "全學期總收費": {
                            "收費期間": "學期",
                            "單價": "72300",
                            "小計": "72300"
                        },
                        "交通費": {
                            "收費期間": "",
                            "單價": "",
                            "小計": ""
                        },
                        "課後延托費": {
                            "收費期間": "月",
                            "單價": "2500",
                            "小計": "15000"
                        },
                        "家長會費": {
                            "收費期間": "",
                            "單價": "",
                            "小計": ""
                        }
                    }
                }
            }
        },
        "3": {
            "上學期": {
                "months": "6",
                "class": {
                    "半日班": {
                        "學費": {
                            "收費期間": "學期",
                            "單價": "",
                            "小計": ""
                        },
                        "雜費": {
                            "收費期間": "月",
                            "單價": "",
                            "小計": ""
                        },
                        "材料費": {
                            "收費期間": "月",
                            "單價": "",
                            "小計": ""
                        },
                        "活動費": {
                            "收費期間": "月",
                            "單價": "",
                            "小計": ""
                        },
                        "午餐費": {
                            "收費期間": "月",
                            "單價": "",
                            "小計": ""
                        },
                        "點心費": {
                            "收費期間": "月",
                            "單價": "",
                            "小計": ""
                        },
                        "全學期總收費": {
                            "收費期間": "學期",
                            "單價": "",
                            "小計": ""
                        },
                        "交通費": {
                            "收費期間": "",
                            "單價": "",
                            "小計": ""
                        },
                        "課後延托費": {
                            "收費期間": "月",
                            "單價": "",
                            "小計": ""
                        },
                        "家長會費": {
                            "收費期間": "",
                            "單價": "",
                            "小計": ""
                        }
                    },
                    "全日班": {
                        "學費": {
                            "收費期間": "學期",
                            "單價": "22800",
                            "小計": "22800"
                        },
                        "雜費": {
                            "收費期間": "月",
                            "單價": "3000",
                            "小計": "18000"
                        },
                        "材料費": {
                            "收費期間": "月",
                            "單價": "850",
                            "小計": "5100"
                        },
                        "活動費": {
                            "收費期間": "月",
                            "單價": "1100",
                            "小計": "6600"
                        },
                        "午餐費": {
                            "收費期間": "月",
                            "單價": "1760",
                            "小計": "10560"
                        },
                        "點心費": {
                            "收費期間": "月",
                            "單價": "1540",
                            "小計": "9240"
                        },
                        "全學期總收費": {
                            "收費期間": "學期",
                            "單價": "72300",
                            "小計": "72300"
                        },
                        "交通費": {
                            "收費期間": "",
                            "單價": "",
                            "小計": ""
                        },
                        "課後延托費": {
                            "收費期間": "月",
                            "單價": "2500",
                            "小計": "15000"
                        },
                        "家長會費": {
                            "收費期間": "",
                            "單價": "",
                            "小計": ""
                        }
                    }
                }
            },
            "下學期": {
                "months": "6",
                "class": {
                    "半日班": {
                        "學費": {
                            "收費期間": "學期",
                            "單價": "",
                            "小計": ""
                        },
                        "雜費": {
                            "收費期間": "月",
                            "單價": "",
                            "小計": ""
                        },
                        "材料費": {
                            "收費期間": "月",
                            "單價": "",
                            "小計": ""
                        },
                        "活動費": {
                            "收費期間": "月",
                            "單價": "",
                            "小計": ""
                        },
                        "午餐費": {
                            "收費期間": "月",
                            "單價": "",
                            "小計": ""
                        },
                        "點心費": {
                            "收費期間": "月",
                            "單價": "",
                            "小計": ""
                        },
                        "全學期總收費": {
                            "收費期間": "學期",
                            "單價": "",
                            "小計": ""
                        },
                        "交通費": {
                            "收費期間": "",
                            "單價": "",
                            "小計": ""
                        },
                        "課後延托費": {
                            "收費期間": "月",
                            "單價": "",
                            "小計": ""
                        },
                        "家長會費": {
                            "收費期間": "",
                            "單價": "",
                            "小計": ""
                        }
                    },
                    "全日班": {
                        "學費": {
                            "收費期間": "學期",
                            "單價": "22800",
                            "小計": "22800"
                        },
                        "雜費": {
                            "收費期間": "月",
                            "單價": "3000",
                            "小計": "18000"
                        },
                        "材料費": {
                            "收費期間": "月",
                            "單價": "850",
                            "小計": "5100"
                        },
                        "活動費": {
                            "收費期間": "月",
                            "單價": "1100",
                            "小計": "6600"
                        },
                        "午餐費": {
                            "收費期間": "月",
                            "單價": "1760",
                            "小計": "10560"
                        },
                        "點心費": {
                            "收費期間": "月",
                            "單價": "1540",
                            "小計": "9240"
                        },
                        "全學期總收費": {
                            "收費期間": "學期",
                            "單價": "72300",
                            "小計": "72300"
                        },
                        "交通費": {
                            "收費期間": "",
                            "單價": "",
                            "小計": ""
                        },
                        "課後延托費": {
                            "收費期間": "月",
                            "單價": "2500",
                            "小計": "15000"
                        },
                        "家長會費": {
                            "收費期間": "",
                            "單價": "",
                            "小計": ""
                        }
                    }
                }
            }
        },
        "2": {
            "上學期": {
                "months": "6",
                "class": {
                    "半日班": {
                        "學費": {
                            "收費期間": "學期",
                            "單價": "",
                            "小計": ""
                        },
                        "雜費": {
                            "收費期間": "月",
                            "單價": "",
                            "小計": ""
                        },
                        "材料費": {
                            "收費期間": "月",
                            "單價": "",
                            "小計": ""
                        },
                        "活動費": {
                            "收費期間": "月",
                            "單價": "",
                            "小計": ""
                        },
                        "午餐費": {
                            "收費期間": "月",
                            "單價": "",
                            "小計": ""
                        },
                        "點心費": {
                            "收費期間": "月",
                            "單價": "",
                            "小計": ""
                        },
                        "全學期總收費": {
                            "收費期間": "學期",
                            "單價": "",
                            "小計": ""
                        },
                        "交通費": {
                            "收費期間": "",
                            "單價": "",
                            "小計": ""
                        },
                        "課後延托費": {
                            "收費期間": "月",
                            "單價": "",
                            "小計": ""
                        },
                        "家長會費": {
                            "收費期間": "",
                            "單價": "",
                            "小計": ""
                        }
                    },
                    "全日班": {
                        "學費": {
                            "收費期間": "學期",
                            "單價": "18800",
                            "小計": "18800"
                        },
                        "雜費": {
                            "收費期間": "月",
                            "單價": "3000",
                            "小計": "18000"
                        },
                        "材料費": {
                            "收費期間": "月",
                            "單價": "1150",
                            "小計": "6900"
                        },
                        "活動費": {
                            "收費期間": "月",
                            "單價": "2000",
                            "小計": "12000"
                        },
                        "午餐費": {
                            "收費期間": "月",
                            "單價": "1760",
                            "小計": "10560"
                        },
                        "點心費": {
                            "收費期間": "月",
                            "單價": "1540",
                            "小計": "9240"
                        },
                        "全學期總收費": {
                            "收費期間": "學期",
                            "單價": "75500",
                            "小計": "75500"
                        },
                        "交通費": {
                            "收費期間": "",
                            "單價": "",
                            "小計": ""
                        },
                        "課後延托費": {
                            "收費期間": "月",
                            "單價": "2500",
                            "小計": "15000"
                        },
                        "家長會費": {
                            "收費期間": "",
                            "單價": "",
                            "小計": ""
                        }
                    }
                }
            },
            "下學期": {
                "months": "6",
                "class": {
                    "半日班": {
                        "學費": {
                            "收費期間": "學期",
                            "單價": "",
                            "小計": ""
                        },
                        "雜費": {
                            "收費期間": "月",
                            "單價": "",
                            "小計": ""
                        },
                        "材料費": {
                            "收費期間": "月",
                            "單價": "",
                            "小計": ""
                        },
                        "活動費": {
                            "收費期間": "月",
                            "單價": "",
                            "小計": ""
                        },
                        "午餐費": {
                            "收費期間": "月",
                            "單價": "",
                            "小計": ""
                        },
                        "點心費": {
                            "收費期間": "月",
                            "單價": "",
                            "小計": ""
                        },
                        "全學期總收費": {
                            "收費期間": "學期",
                            "單價": "",
                            "小計": ""
                        },
                        "交通費": {
                            "收費期間": "",
                            "單價": "",
                            "小計": ""
                        },
                        "課後延托費": {
                            "收費期間": "月",
                            "單價": "",
                            "小計": ""
                        },
                        "家長會費": {
                            "收費期間": "",
                            "單價": "",
                            "小計": ""
                        }
                    },
                    "全日班": {
                        "學費": {
                            "收費期間": "學期",
                            "單價": "18800",
                            "小計": "18800"
                        },
                        "雜費": {
                            "收費期間": "月",
                            "單價": "3000",
                            "小計": "18000"
                        },
                        "材料費": {
                            "收費期間": "月",
                            "單價": "1150",
                            "小計": "6900"
                        },
                        "活動費": {
                            "收費期間": "月",
                            "單價": "2000",
                            "小計": "12000"
                        },
                        "午餐費": {
                            "收費期間": "月",
                            "單價": "1760",
                            "小計": "10560"
                        },
                        "點心費": {
                            "收費期間": "月",
                            "單價": "1540",
                            "小計": "9240"
                        },
                        "全學期總收費": {
                            "收費期間": "學期",
                            "單價": "75500",
                            "小計": "75500"
                        },
                        "交通費": {
                            "收費期間": "",
                            "單價": "",
                            "小計": ""
                        },
                        "課後延托費": {
                            "收費期間": "月",
                            "單價": "2500",
                            "小計": "15000"
                        },
                        "家長會費": {
                            "收費期間": "",
                            "單價": "",
                            "小計": ""
                        }
                    }
                }
            }
        }
    }
}