{
    "type": "Feature",
    "properties": {
        "reg_no": "新北府教幼字第1080003599永和0015之4號",
        "reg_docno": "八二北府教二字第391864號",
        "reg_date": "1993\/10\/22",
        "title": "新北市永和區永和國民小學附設幼兒園",
        "owner": "莊朝欽",
        "city": "新北市",
        "town": "永和區",
        "type": "公立",
        "address": "[234]秀朗路一段120號",
        "floor": "1樓、2樓",
        "size": "1,223平方公尺",
        "size_in": "635.7平方公尺",
        "size_out": "587.3平方公尺",
        "tel": "(02)29213160#600",
        "url": "https:\/\/ntpcyhes601.blogspot.com\/",
        "count_approved": "226",
        "shuttle": "",
        "pre_public": "無",
        "is_free5": "",
        "is_after": "無",
        "penalty": "有",
        "has_slip": "no",
        "id": "827c5813-1b6b-4ba6-8a8c-f398e091e0cb",
        "monthly": 3728,
        "is_active": 1
    },
    "geometry": {
        "type": "Point",
        "coordinates": [
            121.51699,
            25.003609
        ]
    }
}