{
    "type": "Feature",
    "properties": {
        "reg_no": "府教學前字第1030014300號",
        "reg_docno": "府社福字第0940065407號",
        "reg_date": "2005\/06\/08",
        "title": "苗栗縣私立種子幼兒園",
        "owner": "郭宏仁",
        "city": "苗栗縣",
        "town": "竹南鎮",
        "type": "私立",
        "address": "[350]光德路182號",
        "floor": "1樓",
        "size": "834.51平方公尺",
        "size_in": "215.64平方公尺",
        "size_out": "618.87平方公尺",
        "tel": "(037)469320",
        "url": "",
        "count_approved": "70",
        "shuttle": "\t\t",
        "pre_public": "113-115",
        "is_free5": "",
        "is_after": "有，人數：15",
        "penalty": "有",
        "has_slip": "yes",
        "id": "b853b52e-e4f8-4504-9dda-bb5874c0469e",
        "monthly": 4250,
        "is_active": 1
    },
    "geometry": {
        "type": "Point",
        "coordinates": [
            120.8636981,
            24.6718901
        ]
    }
}