{
    "type": "Feature",
    "properties": {
        "reg_no": "北府教幼字第1011259620板橋0021號",
        "reg_docno": "71北府教二字第137212號",
        "reg_date": "1982\/07\/12",
        "title": "新北市私立育樂幼兒園",
        "owner": "林紫駖",
        "city": "新北市",
        "town": "板橋區",
        "type": "私立",
        "address": "[220]民權路260巷1弄14、16號1樓",
        "floor": "一樓",
        "size": "528.94平方公尺",
        "size_in": "363.64平方公尺",
        "size_out": "165.3平方公尺",
        "tel": "(02)29653936",
        "url": "",
        "count_approved": "90",
        "shuttle": "\t\t",
        "pre_public": "無",
        "is_free5": "",
        "is_after": "無",
        "penalty": "有",
        "has_slip": "yes",
        "id": "ea8c388c-307e-4041-854f-8e3d41c8f5cb",
        "monthly": 14950,
        "is_active": 1
    },
    "geometry": {
        "type": "Point",
        "coordinates": [
            121.45798,
            25.015502
        ]
    }
}