{
    "meta": {
        "title": "新北市私立建和幼兒園",
        "city": "新北市",
        "town": "新莊區",
        "type": "私立",
        "address": "[242]中正路149號2樓",
        "tel": "(02)29946699",
        "url": "grace67@kimo.com",
        "count_approved": "80",
        "pre_public": "無",
        "is_free5": "(110)",
        "is_after": "無",
        "penalty": "無",
        "has_slip": "yes"
    },
    "slip": {
        "5": {
            "上學期": {
                "months": "5.5",
                "class": {
                    "半日班": {
                        "學費": {
                            "收費期間": "學期",
                            "單價": "",
                            "小計": ""
                        },
                        "雜費": {
                            "收費期間": "月",
                            "單價": "",
                            "小計": ""
                        },
                        "材料費": {
                            "收費期間": "學期",
                            "單價": "",
                            "小計": ""
                        },
                        "活動費": {
                            "收費期間": "月",
                            "單價": "",
                            "小計": ""
                        },
                        "午餐費": {
                            "收費期間": "月",
                            "單價": "",
                            "小計": ""
                        },
                        "點心費": {
                            "收費期間": "月",
                            "單價": "",
                            "小計": ""
                        },
                        "全學期總收費": {
                            "收費期間": "學期",
                            "單價": "",
                            "小計": ""
                        },
                        "交通費": {
                            "收費期間": "單趟\r\n                                                雙趟",
                            "單價": "",
                            "小計": ""
                        },
                        "課後延托費": {
                            "收費期間": "",
                            "單價": "",
                            "小計": ""
                        },
                        "家長會費": {
                            "收費期間": "",
                            "單價": "",
                            "小計": ""
                        }
                    },
                    "全日班": {
                        "學費": {
                            "收費期間": "學期",
                            "單價": "15000",
                            "小計": "15000"
                        },
                        "雜費": {
                            "收費期間": "月",
                            "單價": "5900",
                            "小計": "32450"
                        },
                        "材料費": {
                            "收費期間": "學期",
                            "單價": "7800",
                            "小計": "7800"
                        },
                        "活動費": {
                            "收費期間": "月",
                            "單價": "1000",
                            "小計": "5500"
                        },
                        "午餐費": {
                            "收費期間": "月",
                            "單價": "1500",
                            "小計": "8250"
                        },
                        "點心費": {
                            "收費期間": "月",
                            "單價": "1000",
                            "小計": "5500"
                        },
                        "全學期總收費": {
                            "收費期間": "學期",
                            "單價": "74500",
                            "小計": "74500"
                        },
                        "交通費": {
                            "收費期間": "單趟\r\n                                                雙趟",
                            "單價": "單\r\n\t\t\t\t\t\t                700\r\n\t\t\t\t\t\t                雙\r\n\t\t\t\t\t\t                1200",
                            "小計": "700\r\n\t\t\t\t\t\t                1200"
                        },
                        "課後延托費": {
                            "收費期間": "",
                            "單價": "",
                            "小計": ""
                        },
                        "家長會費": {
                            "收費期間": "",
                            "單價": "",
                            "小計": ""
                        }
                    }
                }
            },
            "下學期": {
                "months": "5.5",
                "class": {
                    "半日班": {
                        "學費": {
                            "收費期間": "學期",
                            "單價": "",
                            "小計": ""
                        },
                        "雜費": {
                            "收費期間": "月",
                            "單價": "",
                            "小計": ""
                        },
                        "材料費": {
                            "收費期間": "學期",
                            "單價": "",
                            "小計": ""
                        },
                        "活動費": {
                            "收費期間": "月",
                            "單價": "",
                            "小計": ""
                        },
                        "午餐費": {
                            "收費期間": "月",
                            "單價": "",
                            "小計": ""
                        },
                        "點心費": {
                            "收費期間": "月",
                            "單價": "",
                            "小計": ""
                        },
                        "全學期總收費": {
                            "收費期間": "學期",
                            "單價": "",
                            "小計": ""
                        },
                        "交通費": {
                            "收費期間": "單趟\r\n                                                雙趟",
                            "單價": "",
                            "小計": ""
                        },
                        "課後延托費": {
                            "收費期間": "",
                            "單價": "",
                            "小計": ""
                        },
                        "家長會費": {
                            "收費期間": "",
                            "單價": "",
                            "小計": ""
                        }
                    },
                    "全日班": {
                        "學費": {
                            "收費期間": "學期",
                            "單價": "15000",
                            "小計": "15000"
                        },
                        "雜費": {
                            "收費期間": "月",
                            "單價": "5900",
                            "小計": "32450"
                        },
                        "材料費": {
                            "收費期間": "學期",
                            "單價": "7800",
                            "小計": "7800"
                        },
                        "活動費": {
                            "收費期間": "月",
                            "單價": "1000",
                            "小計": "5500"
                        },
                        "午餐費": {
                            "收費期間": "月",
                            "單價": "1500",
                            "小計": "8250"
                        },
                        "點心費": {
                            "收費期間": "月",
                            "單價": "1000",
                            "小計": "5500"
                        },
                        "全學期總收費": {
                            "收費期間": "學期",
                            "單價": "74500",
                            "小計": "74500"
                        },
                        "交通費": {
                            "收費期間": "單趟\r\n                                                雙趟",
                            "單價": "單\r\n\t\t\t\t\t\t                700\r\n\t\t\t\t\t\t                雙\r\n\t\t\t\t\t\t                1200",
                            "小計": "700\r\n\t\t\t\t\t\t                1200"
                        },
                        "課後延托費": {
                            "收費期間": "",
                            "單價": "",
                            "小計": ""
                        },
                        "家長會費": {
                            "收費期間": "",
                            "單價": "",
                            "小計": ""
                        }
                    }
                }
            }
        },
        "4": {
            "上學期": {
                "months": "5.5",
                "class": {
                    "半日班": {
                        "學費": {
                            "收費期間": "學期",
                            "單價": "15000",
                            "小計": "15000"
                        },
                        "雜費": {
                            "收費期間": "月",
                            "單價": "4300",
                            "小計": "23650"
                        },
                        "材料費": {
                            "收費期間": "學期",
                            "單價": "2000",
                            "小計": "2000"
                        },
                        "活動費": {
                            "收費期間": "月",
                            "單價": "1000",
                            "小計": "5500"
                        },
                        "午餐費": {
                            "收費期間": "月",
                            "單價": "",
                            "小計": ""
                        },
                        "點心費": {
                            "收費期間": "月",
                            "單價": "1000",
                            "小計": "5500"
                        },
                        "全學期總收費": {
                            "收費期間": "學期",
                            "單價": "51650",
                            "小計": "51650"
                        },
                        "交通費": {
                            "收費期間": "單趟\r\n                                                    雙趟",
                            "單價": "",
                            "小計": ""
                        },
                        "課後延托費": {
                            "收費期間": "月",
                            "單價": "",
                            "小計": ""
                        },
                        "家長會費": {
                            "收費期間": "",
                            "單價": "",
                            "小計": ""
                        }
                    },
                    "全日班": {
                        "學費": {
                            "收費期間": "學期",
                            "單價": "15000",
                            "小計": "15000"
                        },
                        "雜費": {
                            "收費期間": "月",
                            "單價": "6400",
                            "小計": "35200"
                        },
                        "材料費": {
                            "收費期間": "學期",
                            "單價": "7800",
                            "小計": "7800"
                        },
                        "活動費": {
                            "收費期間": "月",
                            "單價": "1000",
                            "小計": "5500"
                        },
                        "午餐費": {
                            "收費期間": "月",
                            "單價": "1500",
                            "小計": "8250"
                        },
                        "點心費": {
                            "收費期間": "月",
                            "單價": "1000",
                            "小計": "5500"
                        },
                        "全學期總收費": {
                            "收費期間": "學期",
                            "單價": "77250",
                            "小計": "77250"
                        },
                        "交通費": {
                            "收費期間": "單趟\r\n                                                    雙趟",
                            "單價": "單\r\n\t\t\t\t\t\t\t                700\r\n\t\t\t\t\t\t\t                雙\r\n\t\t\t\t\t\t\t                1200",
                            "小計": "700\r\n\t\t\t\t\t\t\t                1200"
                        },
                        "課後延托費": {
                            "收費期間": "月",
                            "單價": "2200",
                            "小計": "12100"
                        },
                        "家長會費": {
                            "收費期間": "",
                            "單價": "",
                            "小計": ""
                        }
                    }
                }
            },
            "下學期": {
                "months": "5.5",
                "class": {
                    "半日班": {
                        "學費": {
                            "收費期間": "學期",
                            "單價": "15000",
                            "小計": "15000"
                        },
                        "雜費": {
                            "收費期間": "月",
                            "單價": "4300",
                            "小計": "23650"
                        },
                        "材料費": {
                            "收費期間": "學期",
                            "單價": "2000",
                            "小計": "2000"
                        },
                        "活動費": {
                            "收費期間": "月",
                            "單價": "1000",
                            "小計": "5500"
                        },
                        "午餐費": {
                            "收費期間": "月",
                            "單價": "",
                            "小計": ""
                        },
                        "點心費": {
                            "收費期間": "月",
                            "單價": "1000",
                            "小計": "5500"
                        },
                        "全學期總收費": {
                            "收費期間": "學期",
                            "單價": "51650",
                            "小計": "51650"
                        },
                        "交通費": {
                            "收費期間": "單趟\r\n                                                    雙趟",
                            "單價": "",
                            "小計": ""
                        },
                        "課後延托費": {
                            "收費期間": "月",
                            "單價": "",
                            "小計": ""
                        },
                        "家長會費": {
                            "收費期間": "",
                            "單價": "",
                            "小計": ""
                        }
                    },
                    "全日班": {
                        "學費": {
                            "收費期間": "學期",
                            "單價": "15000",
                            "小計": "15000"
                        },
                        "雜費": {
                            "收費期間": "月",
                            "單價": "6400",
                            "小計": "35200"
                        },
                        "材料費": {
                            "收費期間": "學期",
                            "單價": "7800",
                            "小計": "7800"
                        },
                        "活動費": {
                            "收費期間": "月",
                            "單價": "1000",
                            "小計": "5500"
                        },
                        "午餐費": {
                            "收費期間": "月",
                            "單價": "1500",
                            "小計": "8250"
                        },
                        "點心費": {
                            "收費期間": "月",
                            "單價": "1000",
                            "小計": "5500"
                        },
                        "全學期總收費": {
                            "收費期間": "學期",
                            "單價": "77250",
                            "小計": "77250"
                        },
                        "交通費": {
                            "收費期間": "單趟\r\n                                                    雙趟",
                            "單價": "單\r\n\t\t\t\t\t\t\t                700\r\n\t\t\t\t\t\t\t                雙\r\n\t\t\t\t\t\t\t                1200",
                            "小計": "700\r\n\t\t\t\t\t\t\t                1200"
                        },
                        "課後延托費": {
                            "收費期間": "月",
                            "單價": "2200",
                            "小計": "12100"
                        },
                        "家長會費": {
                            "收費期間": "",
                            "單價": "",
                            "小計": ""
                        }
                    }
                }
            }
        },
        "3": {
            "上學期": {
                "months": "5.5",
                "class": {
                    "半日班": {
                        "學費": {
                            "收費期間": "學期",
                            "單價": "15000",
                            "小計": "15000"
                        },
                        "雜費": {
                            "收費期間": "月",
                            "單價": "4300",
                            "小計": "23650"
                        },
                        "材料費": {
                            "收費期間": "學期",
                            "單價": "2000",
                            "小計": "2000"
                        },
                        "活動費": {
                            "收費期間": "月",
                            "單價": "1000",
                            "小計": "5500"
                        },
                        "午餐費": {
                            "收費期間": "月",
                            "單價": "",
                            "小計": ""
                        },
                        "點心費": {
                            "收費期間": "月",
                            "單價": "1000",
                            "小計": "5500"
                        },
                        "全學期總收費": {
                            "收費期間": "學期",
                            "單價": "51650",
                            "小計": "51650"
                        },
                        "交通費": {
                            "收費期間": "單趟\r\n                                                    雙趟",
                            "單價": "",
                            "小計": ""
                        },
                        "課後延托費": {
                            "收費期間": "月",
                            "單價": "",
                            "小計": ""
                        },
                        "家長會費": {
                            "收費期間": "",
                            "單價": "",
                            "小計": ""
                        }
                    },
                    "全日班": {
                        "學費": {
                            "收費期間": "學期",
                            "單價": "15000",
                            "小計": "15000"
                        },
                        "雜費": {
                            "收費期間": "月",
                            "單價": "6400",
                            "小計": "35200"
                        },
                        "材料費": {
                            "收費期間": "學期",
                            "單價": "7800",
                            "小計": "7800"
                        },
                        "活動費": {
                            "收費期間": "月",
                            "單價": "1000",
                            "小計": "5500"
                        },
                        "午餐費": {
                            "收費期間": "月",
                            "單價": "1500",
                            "小計": "8250"
                        },
                        "點心費": {
                            "收費期間": "月",
                            "單價": "1000",
                            "小計": "5500"
                        },
                        "全學期總收費": {
                            "收費期間": "學期",
                            "單價": "77250",
                            "小計": "77250"
                        },
                        "交通費": {
                            "收費期間": "單趟\r\n                                                    雙趟",
                            "單價": "單\r\n\t\t\t\t\t\t\t                700\r\n\t\t\t\t\t\t\t                雙\r\n\t\t\t\t\t\t\t                1200",
                            "小計": "700\r\n\t\t\t\t\t\t\t                1200"
                        },
                        "課後延托費": {
                            "收費期間": "月",
                            "單價": "2200",
                            "小計": "12100"
                        },
                        "家長會費": {
                            "收費期間": "",
                            "單價": "",
                            "小計": ""
                        }
                    }
                }
            },
            "下學期": {
                "months": "5.5",
                "class": {
                    "半日班": {
                        "學費": {
                            "收費期間": "學期",
                            "單價": "15000",
                            "小計": "15000"
                        },
                        "雜費": {
                            "收費期間": "月",
                            "單價": "4300",
                            "小計": "23650"
                        },
                        "材料費": {
                            "收費期間": "學期",
                            "單價": "2000",
                            "小計": "2000"
                        },
                        "活動費": {
                            "收費期間": "月",
                            "單價": "1000",
                            "小計": "5500"
                        },
                        "午餐費": {
                            "收費期間": "月",
                            "單價": "",
                            "小計": ""
                        },
                        "點心費": {
                            "收費期間": "月",
                            "單價": "1000",
                            "小計": "5500"
                        },
                        "全學期總收費": {
                            "收費期間": "學期",
                            "單價": "51650",
                            "小計": "51650"
                        },
                        "交通費": {
                            "收費期間": "單趟\r\n                                                    雙趟",
                            "單價": "",
                            "小計": ""
                        },
                        "課後延托費": {
                            "收費期間": "月",
                            "單價": "",
                            "小計": ""
                        },
                        "家長會費": {
                            "收費期間": "",
                            "單價": "",
                            "小計": ""
                        }
                    },
                    "全日班": {
                        "學費": {
                            "收費期間": "學期",
                            "單價": "15000",
                            "小計": "15000"
                        },
                        "雜費": {
                            "收費期間": "月",
                            "單價": "6400",
                            "小計": "35200"
                        },
                        "材料費": {
                            "收費期間": "學期",
                            "單價": "7800",
                            "小計": "7800"
                        },
                        "活動費": {
                            "收費期間": "月",
                            "單價": "1000",
                            "小計": "5500"
                        },
                        "午餐費": {
                            "收費期間": "月",
                            "單價": "1500",
                            "小計": "8250"
                        },
                        "點心費": {
                            "收費期間": "月",
                            "單價": "1000",
                            "小計": "5500"
                        },
                        "全學期總收費": {
                            "收費期間": "學期",
                            "單價": "77250",
                            "小計": "77250"
                        },
                        "交通費": {
                            "收費期間": "單趟\r\n                                                    雙趟",
                            "單價": "單\r\n\t\t\t\t\t\t\t                700\r\n\t\t\t\t\t\t\t                雙\r\n\t\t\t\t\t\t\t                1200",
                            "小計": "700\r\n\t\t\t\t\t\t\t                1200"
                        },
                        "課後延托費": {
                            "收費期間": "月",
                            "單價": "2200",
                            "小計": "12100"
                        },
                        "家長會費": {
                            "收費期間": "",
                            "單價": "",
                            "小計": ""
                        }
                    }
                }
            }
        },
        "2": {
            "上學期": {
                "months": "5.5",
                "class": {
                    "半日班": {
                        "學費": {
                            "收費期間": "學期",
                            "單價": "15000",
                            "小計": "15000"
                        },
                        "雜費": {
                            "收費期間": "月",
                            "單價": "4500",
                            "小計": "24750"
                        },
                        "材料費": {
                            "收費期間": "學期",
                            "單價": "2000",
                            "小計": "2000"
                        },
                        "活動費": {
                            "收費期間": "月",
                            "單價": "1000",
                            "小計": "5500"
                        },
                        "午餐費": {
                            "收費期間": "月",
                            "單價": "",
                            "小計": ""
                        },
                        "點心費": {
                            "收費期間": "月",
                            "單價": "1000",
                            "小計": "5500"
                        },
                        "全學期總收費": {
                            "收費期間": "學期",
                            "單價": "52750",
                            "小計": "52750"
                        },
                        "交通費": {
                            "收費期間": "單趟\r\n                                                    雙趟",
                            "單價": "",
                            "小計": ""
                        },
                        "課後延托費": {
                            "收費期間": "月",
                            "單價": "",
                            "小計": ""
                        },
                        "家長會費": {
                            "收費期間": "",
                            "單價": "",
                            "小計": ""
                        }
                    },
                    "全日班": {
                        "學費": {
                            "收費期間": "學期",
                            "單價": "15000",
                            "小計": "15000"
                        },
                        "雜費": {
                            "收費期間": "月",
                            "單價": "6900",
                            "小計": "37950"
                        },
                        "材料費": {
                            "收費期間": "學期",
                            "單價": "7800",
                            "小計": "7800"
                        },
                        "活動費": {
                            "收費期間": "月",
                            "單價": "1000",
                            "小計": "5500"
                        },
                        "午餐費": {
                            "收費期間": "月",
                            "單價": "1500",
                            "小計": "8250"
                        },
                        "點心費": {
                            "收費期間": "月",
                            "單價": "1000",
                            "小計": "5500"
                        },
                        "全學期總收費": {
                            "收費期間": "學期",
                            "單價": "80000",
                            "小計": "80000"
                        },
                        "交通費": {
                            "收費期間": "單趟\r\n                                                    雙趟",
                            "單價": "單\r\n\t\t\t\t\t\t\t                700\r\n\t\t\t\t\t\t\t                雙\r\n\t\t\t\t\t\t\t                1200",
                            "小計": "700\r\n\t\t\t\t\t\t\t                1200"
                        },
                        "課後延托費": {
                            "收費期間": "月",
                            "單價": "2200",
                            "小計": "12100"
                        },
                        "家長會費": {
                            "收費期間": "",
                            "單價": "",
                            "小計": ""
                        }
                    }
                }
            },
            "下學期": {
                "months": "5.5",
                "class": {
                    "半日班": {
                        "學費": {
                            "收費期間": "學期",
                            "單價": "15000",
                            "小計": "15000"
                        },
                        "雜費": {
                            "收費期間": "月",
                            "單價": "4500",
                            "小計": "24750"
                        },
                        "材料費": {
                            "收費期間": "學期",
                            "單價": "2000",
                            "小計": "2000"
                        },
                        "活動費": {
                            "收費期間": "月",
                            "單價": "1000",
                            "小計": "5500"
                        },
                        "午餐費": {
                            "收費期間": "月",
                            "單價": "",
                            "小計": ""
                        },
                        "點心費": {
                            "收費期間": "月",
                            "單價": "1000",
                            "小計": "5500"
                        },
                        "全學期總收費": {
                            "收費期間": "學期",
                            "單價": "52750",
                            "小計": "52750"
                        },
                        "交通費": {
                            "收費期間": "單趟\r\n                                                    雙趟",
                            "單價": "",
                            "小計": ""
                        },
                        "課後延托費": {
                            "收費期間": "月",
                            "單價": "",
                            "小計": ""
                        },
                        "家長會費": {
                            "收費期間": "",
                            "單價": "",
                            "小計": ""
                        }
                    },
                    "全日班": {
                        "學費": {
                            "收費期間": "學期",
                            "單價": "15000",
                            "小計": "15000"
                        },
                        "雜費": {
                            "收費期間": "月",
                            "單價": "6900",
                            "小計": "37950"
                        },
                        "材料費": {
                            "收費期間": "學期",
                            "單價": "7800",
                            "小計": "7800"
                        },
                        "活動費": {
                            "收費期間": "月",
                            "單價": "1000",
                            "小計": "5500"
                        },
                        "午餐費": {
                            "收費期間": "月",
                            "單價": "1500",
                            "小計": "8250"
                        },
                        "點心費": {
                            "收費期間": "月",
                            "單價": "1000",
                            "小計": "5500"
                        },
                        "全學期總收費": {
                            "收費期間": "學期",
                            "單價": "80000",
                            "小計": "80000"
                        },
                        "交通費": {
                            "收費期間": "單趟\r\n                                                    雙趟",
                            "單價": "單\r\n\t\t\t\t\t\t\t                700\r\n\t\t\t\t\t\t\t                雙\r\n\t\t\t\t\t\t\t                1200",
                            "小計": "700\r\n\t\t\t\t\t\t\t                1200"
                        },
                        "課後延托費": {
                            "收費期間": "月",
                            "單價": "2200",
                            "小計": "12100"
                        },
                        "家長會費": {
                            "收費期間": "",
                            "單價": "",
                            "小計": ""
                        }
                    }
                }
            }
        }
    }
}