{
    "meta": {
        "reg_no": "府教幼字第1090254590號",
        "reg_docno": "府社婦字第094032329號",
        "reg_date": "2005\/11\/17",
        "title": "桃園市私立美加達幼兒園",
        "owner": "胡貞綺",
        "city": "桃園市",
        "town": "楊梅區",
        "type": "私立",
        "address": "[326]中山北路一段390巷45弄29號1-3樓、29-1號1-3樓",
        "floor": "1-3樓",
        "size": "599.92平方公尺",
        "size_in": "439.36平方公尺",
        "size_out": "160.56平方公尺",
        "tel": "(03)4787855",
        "url": "",
        "count_approved": "170",
        "shuttle": "\t\t",
        "pre_public": "110-112",
        "is_free5": "",
        "is_after": "有，人數：20",
        "penalty": "有",
        "has_slip": "no"
    },
    "slip": {
        "5": {
            "上學期": {
                "months": "6",
                "class": {
                    "半日班": {
                        "學費": {
                            "收費期間": "學期",
                            "單價": "",
                            "小計": ""
                        },
                        "雜費": {
                            "收費期間": "月",
                            "單價": "",
                            "小計": ""
                        },
                        "材料費": {
                            "收費期間": "月",
                            "單價": "",
                            "小計": ""
                        },
                        "活動費": {
                            "收費期間": "月",
                            "單價": "",
                            "小計": ""
                        },
                        "午餐費": {
                            "收費期間": "月",
                            "單價": "",
                            "小計": ""
                        },
                        "點心費": {
                            "收費期間": "月",
                            "單價": "",
                            "小計": ""
                        },
                        "全學期總收費": {
                            "收費期間": "學期",
                            "單價": "",
                            "小計": ""
                        },
                        "交通費": {
                            "收費期間": "單趟\r\n                                                雙趟",
                            "單價": "",
                            "小計": ""
                        },
                        "課後延托費": {
                            "收費期間": "月",
                            "單價": "",
                            "小計": ""
                        },
                        "家長會費": {
                            "收費期間": "",
                            "單價": "",
                            "小計": ""
                        }
                    },
                    "全日班": {
                        "學費": {
                            "收費期間": "學期",
                            "單價": "15000",
                            "小計": "15000"
                        },
                        "雜費": {
                            "收費期間": "月",
                            "單價": "3414",
                            "小計": "20484"
                        },
                        "材料費": {
                            "收費期間": "月",
                            "單價": "416",
                            "小計": "2496"
                        },
                        "活動費": {
                            "收費期間": "月",
                            "單價": "360",
                            "小計": "2160"
                        },
                        "午餐費": {
                            "收費期間": "月",
                            "單價": "876",
                            "小計": "5256"
                        },
                        "點心費": {
                            "收費期間": "月",
                            "單價": "1124",
                            "小計": "6744"
                        },
                        "全學期總收費": {
                            "收費期間": "學期",
                            "單價": "52140",
                            "小計": "52140"
                        },
                        "交通費": {
                            "收費期間": "單趟\r\n                                                雙趟",
                            "單價": "單\r\n\t\t\t\t\t\t                600\r\n\t\t\t\t\t\t                雙\r\n\t\t\t\t\t\t                1200",
                            "小計": "600\r\n\t\t\t\t\t\t                1200"
                        },
                        "課後延托費": {
                            "收費期間": "月",
                            "單價": "1500",
                            "小計": "9000"
                        },
                        "家長會費": {
                            "收費期間": "",
                            "單價": "",
                            "小計": ""
                        }
                    }
                }
            },
            "下學期": {
                "months": "6",
                "class": {
                    "半日班": {
                        "學費": {
                            "收費期間": "學期",
                            "單價": "",
                            "小計": ""
                        },
                        "雜費": {
                            "收費期間": "月",
                            "單價": "",
                            "小計": ""
                        },
                        "材料費": {
                            "收費期間": "月",
                            "單價": "",
                            "小計": ""
                        },
                        "活動費": {
                            "收費期間": "月",
                            "單價": "",
                            "小計": ""
                        },
                        "午餐費": {
                            "收費期間": "月",
                            "單價": "",
                            "小計": ""
                        },
                        "點心費": {
                            "收費期間": "月",
                            "單價": "",
                            "小計": ""
                        },
                        "全學期總收費": {
                            "收費期間": "學期",
                            "單價": "",
                            "小計": ""
                        },
                        "交通費": {
                            "收費期間": "單趟\r\n                                                雙趟",
                            "單價": "",
                            "小計": ""
                        },
                        "課後延托費": {
                            "收費期間": "月",
                            "單價": "",
                            "小計": ""
                        },
                        "家長會費": {
                            "收費期間": "",
                            "單價": "",
                            "小計": ""
                        }
                    },
                    "全日班": {
                        "學費": {
                            "收費期間": "學期",
                            "單價": "15000",
                            "小計": "15000"
                        },
                        "雜費": {
                            "收費期間": "月",
                            "單價": "3414",
                            "小計": "20484"
                        },
                        "材料費": {
                            "收費期間": "月",
                            "單價": "416",
                            "小計": "2496"
                        },
                        "活動費": {
                            "收費期間": "月",
                            "單價": "360",
                            "小計": "2160"
                        },
                        "午餐費": {
                            "收費期間": "月",
                            "單價": "876",
                            "小計": "5256"
                        },
                        "點心費": {
                            "收費期間": "月",
                            "單價": "1124",
                            "小計": "6744"
                        },
                        "全學期總收費": {
                            "收費期間": "學期",
                            "單價": "52140",
                            "小計": "52140"
                        },
                        "交通費": {
                            "收費期間": "單趟\r\n                                                雙趟",
                            "單價": "單\r\n\t\t\t\t\t\t                600\r\n\t\t\t\t\t\t                雙\r\n\t\t\t\t\t\t                1200",
                            "小計": "600\r\n\t\t\t\t\t\t                1200"
                        },
                        "課後延托費": {
                            "收費期間": "月",
                            "單價": "1500",
                            "小計": "9000"
                        },
                        "家長會費": {
                            "收費期間": "",
                            "單價": "",
                            "小計": ""
                        }
                    }
                }
            }
        },
        "4": {
            "上學期": {
                "months": "6",
                "class": {
                    "半日班": {
                        "學費": {
                            "收費期間": "學期",
                            "單價": "",
                            "小計": ""
                        },
                        "雜費": {
                            "收費期間": "學期",
                            "單價": "",
                            "小計": ""
                        },
                        "材料費": {
                            "收費期間": "月",
                            "單價": "",
                            "小計": ""
                        },
                        "活動費": {
                            "收費期間": "月",
                            "單價": "",
                            "小計": ""
                        },
                        "午餐費": {
                            "收費期間": "月",
                            "單價": "",
                            "小計": ""
                        },
                        "點心費": {
                            "收費期間": "月",
                            "單價": "",
                            "小計": ""
                        },
                        "全學期總收費": {
                            "收費期間": "學期",
                            "單價": "",
                            "小計": ""
                        },
                        "交通費": {
                            "收費期間": "單趟\r\n                                                    雙趟",
                            "單價": "",
                            "小計": ""
                        },
                        "課後延托費": {
                            "收費期間": "月",
                            "單價": "",
                            "小計": ""
                        },
                        "家長會費": {
                            "收費期間": "",
                            "單價": "",
                            "小計": ""
                        }
                    },
                    "全日班": {
                        "學費": {
                            "收費期間": "學期",
                            "單價": "15000",
                            "小計": "15000"
                        },
                        "雜費": {
                            "收費期間": "學期",
                            "單價": "10442",
                            "小計": "10442"
                        },
                        "材料費": {
                            "收費期間": "月",
                            "單價": "1700",
                            "小計": "10200"
                        },
                        "活動費": {
                            "收費期間": "月",
                            "單價": "1100",
                            "小計": "6600"
                        },
                        "午餐費": {
                            "收費期間": "月",
                            "單價": "1000",
                            "小計": "6000"
                        },
                        "點心費": {
                            "收費期間": "月",
                            "單價": "1200",
                            "小計": "7200"
                        },
                        "全學期總收費": {
                            "收費期間": "學期",
                            "單價": "55442",
                            "小計": "55442"
                        },
                        "交通費": {
                            "收費期間": "單趟\r\n                                                    雙趟",
                            "單價": "單\r\n\t\t\t\t\t\t\t                600\r\n\t\t\t\t\t\t\t                雙\r\n\t\t\t\t\t\t\t                1200",
                            "小計": "600\r\n\t\t\t\t\t\t\t                1200"
                        },
                        "課後延托費": {
                            "收費期間": "月",
                            "單價": "1500",
                            "小計": "9000"
                        },
                        "家長會費": {
                            "收費期間": "",
                            "單價": "",
                            "小計": ""
                        }
                    }
                }
            },
            "下學期": {
                "months": "6",
                "class": {
                    "半日班": {
                        "學費": {
                            "收費期間": "學期",
                            "單價": "",
                            "小計": ""
                        },
                        "雜費": {
                            "收費期間": "學期",
                            "單價": "",
                            "小計": ""
                        },
                        "材料費": {
                            "收費期間": "月",
                            "單價": "",
                            "小計": ""
                        },
                        "活動費": {
                            "收費期間": "月",
                            "單價": "",
                            "小計": ""
                        },
                        "午餐費": {
                            "收費期間": "月",
                            "單價": "",
                            "小計": ""
                        },
                        "點心費": {
                            "收費期間": "月",
                            "單價": "",
                            "小計": ""
                        },
                        "全學期總收費": {
                            "收費期間": "學期",
                            "單價": "",
                            "小計": ""
                        },
                        "交通費": {
                            "收費期間": "單趟\r\n                                                    雙趟",
                            "單價": "",
                            "小計": ""
                        },
                        "課後延托費": {
                            "收費期間": "月",
                            "單價": "",
                            "小計": ""
                        },
                        "家長會費": {
                            "收費期間": "",
                            "單價": "",
                            "小計": ""
                        }
                    },
                    "全日班": {
                        "學費": {
                            "收費期間": "學期",
                            "單價": "15000",
                            "小計": "15000"
                        },
                        "雜費": {
                            "收費期間": "學期",
                            "單價": "10442",
                            "小計": "10442"
                        },
                        "材料費": {
                            "收費期間": "月",
                            "單價": "1700",
                            "小計": "10200"
                        },
                        "活動費": {
                            "收費期間": "月",
                            "單價": "1100",
                            "小計": "6600"
                        },
                        "午餐費": {
                            "收費期間": "月",
                            "單價": "1000",
                            "小計": "6000"
                        },
                        "點心費": {
                            "收費期間": "月",
                            "單價": "1200",
                            "小計": "7200"
                        },
                        "全學期總收費": {
                            "收費期間": "學期",
                            "單價": "55442",
                            "小計": "55442"
                        },
                        "交通費": {
                            "收費期間": "單趟\r\n                                                    雙趟",
                            "單價": "單\r\n\t\t\t\t\t\t\t                600\r\n\t\t\t\t\t\t\t                雙\r\n\t\t\t\t\t\t\t                1200",
                            "小計": "600\r\n\t\t\t\t\t\t\t                1200"
                        },
                        "課後延托費": {
                            "收費期間": "月",
                            "單價": "1500",
                            "小計": "9000"
                        },
                        "家長會費": {
                            "收費期間": "",
                            "單價": "",
                            "小計": ""
                        }
                    }
                }
            }
        },
        "3": {
            "上學期": {
                "months": "6",
                "class": {
                    "半日班": {
                        "學費": {
                            "收費期間": "學期",
                            "單價": "",
                            "小計": ""
                        },
                        "雜費": {
                            "收費期間": "學期",
                            "單價": "",
                            "小計": ""
                        },
                        "材料費": {
                            "收費期間": "月",
                            "單價": "",
                            "小計": ""
                        },
                        "活動費": {
                            "收費期間": "月",
                            "單價": "",
                            "小計": ""
                        },
                        "午餐費": {
                            "收費期間": "月",
                            "單價": "",
                            "小計": ""
                        },
                        "點心費": {
                            "收費期間": "月",
                            "單價": "",
                            "小計": ""
                        },
                        "全學期總收費": {
                            "收費期間": "學期",
                            "單價": "",
                            "小計": ""
                        },
                        "交通費": {
                            "收費期間": "單趟\r\n                                                    雙趟",
                            "單價": "",
                            "小計": ""
                        },
                        "課後延托費": {
                            "收費期間": "月",
                            "單價": "",
                            "小計": ""
                        },
                        "家長會費": {
                            "收費期間": "",
                            "單價": "",
                            "小計": ""
                        }
                    },
                    "全日班": {
                        "學費": {
                            "收費期間": "學期",
                            "單價": "15000",
                            "小計": "15000"
                        },
                        "雜費": {
                            "收費期間": "學期",
                            "單價": "10442",
                            "小計": "10442"
                        },
                        "材料費": {
                            "收費期間": "月",
                            "單價": "1700",
                            "小計": "10200"
                        },
                        "活動費": {
                            "收費期間": "月",
                            "單價": "1100",
                            "小計": "6600"
                        },
                        "午餐費": {
                            "收費期間": "月",
                            "單價": "1000",
                            "小計": "6000"
                        },
                        "點心費": {
                            "收費期間": "月",
                            "單價": "1200",
                            "小計": "7200"
                        },
                        "全學期總收費": {
                            "收費期間": "學期",
                            "單價": "55442",
                            "小計": "55442"
                        },
                        "交通費": {
                            "收費期間": "單趟\r\n                                                    雙趟",
                            "單價": "單\r\n\t\t\t\t\t\t\t                600\r\n\t\t\t\t\t\t\t                雙\r\n\t\t\t\t\t\t\t                1200",
                            "小計": "600\r\n\t\t\t\t\t\t\t                1200"
                        },
                        "課後延托費": {
                            "收費期間": "月",
                            "單價": "1500",
                            "小計": "9000"
                        },
                        "家長會費": {
                            "收費期間": "",
                            "單價": "",
                            "小計": ""
                        }
                    }
                }
            },
            "下學期": {
                "months": "6",
                "class": {
                    "半日班": {
                        "學費": {
                            "收費期間": "學期",
                            "單價": "",
                            "小計": ""
                        },
                        "雜費": {
                            "收費期間": "學期",
                            "單價": "",
                            "小計": ""
                        },
                        "材料費": {
                            "收費期間": "月",
                            "單價": "",
                            "小計": ""
                        },
                        "活動費": {
                            "收費期間": "月",
                            "單價": "",
                            "小計": ""
                        },
                        "午餐費": {
                            "收費期間": "月",
                            "單價": "",
                            "小計": ""
                        },
                        "點心費": {
                            "收費期間": "月",
                            "單價": "",
                            "小計": ""
                        },
                        "全學期總收費": {
                            "收費期間": "學期",
                            "單價": "",
                            "小計": ""
                        },
                        "交通費": {
                            "收費期間": "單趟\r\n                                                    雙趟",
                            "單價": "",
                            "小計": ""
                        },
                        "課後延托費": {
                            "收費期間": "月",
                            "單價": "",
                            "小計": ""
                        },
                        "家長會費": {
                            "收費期間": "",
                            "單價": "",
                            "小計": ""
                        }
                    },
                    "全日班": {
                        "學費": {
                            "收費期間": "學期",
                            "單價": "15000",
                            "小計": "15000"
                        },
                        "雜費": {
                            "收費期間": "學期",
                            "單價": "10442",
                            "小計": "10442"
                        },
                        "材料費": {
                            "收費期間": "月",
                            "單價": "1700",
                            "小計": "10200"
                        },
                        "活動費": {
                            "收費期間": "月",
                            "單價": "1100",
                            "小計": "6600"
                        },
                        "午餐費": {
                            "收費期間": "月",
                            "單價": "1000",
                            "小計": "6000"
                        },
                        "點心費": {
                            "收費期間": "月",
                            "單價": "1200",
                            "小計": "7200"
                        },
                        "全學期總收費": {
                            "收費期間": "學期",
                            "單價": "55442",
                            "小計": "55442"
                        },
                        "交通費": {
                            "收費期間": "單趟\r\n                                                    雙趟",
                            "單價": "單\r\n\t\t\t\t\t\t\t                600\r\n\t\t\t\t\t\t\t                雙\r\n\t\t\t\t\t\t\t                1200",
                            "小計": "600\r\n\t\t\t\t\t\t\t                1200"
                        },
                        "課後延托費": {
                            "收費期間": "月",
                            "單價": "1500",
                            "小計": "9000"
                        },
                        "家長會費": {
                            "收費期間": "",
                            "單價": "",
                            "小計": ""
                        }
                    }
                }
            }
        },
        "2": {
            "上學期": {
                "months": "6",
                "class": {
                    "半日班": {
                        "學費": {
                            "收費期間": "學期",
                            "單價": "",
                            "小計": ""
                        },
                        "雜費": {
                            "收費期間": "月",
                            "單價": "",
                            "小計": ""
                        },
                        "材料費": {
                            "收費期間": "月",
                            "單價": "",
                            "小計": ""
                        },
                        "活動費": {
                            "收費期間": "月",
                            "單價": "",
                            "小計": ""
                        },
                        "午餐費": {
                            "收費期間": "月",
                            "單價": "",
                            "小計": ""
                        },
                        "點心費": {
                            "收費期間": "月",
                            "單價": "",
                            "小計": ""
                        },
                        "全學期總收費": {
                            "收費期間": "學期",
                            "單價": "",
                            "小計": ""
                        },
                        "交通費": {
                            "收費期間": "單趟\r\n                                                    雙趟",
                            "單價": "",
                            "小計": ""
                        },
                        "課後延托費": {
                            "收費期間": "月",
                            "單價": "",
                            "小計": ""
                        },
                        "家長會費": {
                            "收費期間": "",
                            "單價": "",
                            "小計": ""
                        }
                    },
                    "全日班": {
                        "學費": {
                            "收費期間": "學期",
                            "單價": "15000",
                            "小計": "15000"
                        },
                        "雜費": {
                            "收費期間": "月",
                            "單價": "1690",
                            "小計": "10140"
                        },
                        "材料費": {
                            "收費期間": "月",
                            "單價": "2800",
                            "小計": "16800"
                        },
                        "活動費": {
                            "收費期間": "月",
                            "單價": "2000",
                            "小計": "12000"
                        },
                        "午餐費": {
                            "收費期間": "月",
                            "單價": "1000",
                            "小計": "6000"
                        },
                        "點心費": {
                            "收費期間": "月",
                            "單價": "1200",
                            "小計": "7200"
                        },
                        "全學期總收費": {
                            "收費期間": "學期",
                            "單價": "67140",
                            "小計": "67140"
                        },
                        "交通費": {
                            "收費期間": "單趟\r\n                                                    雙趟",
                            "單價": "單\r\n\t\t\t\t\t\t\t                600\r\n\t\t\t\t\t\t\t                雙\r\n\t\t\t\t\t\t\t                1200",
                            "小計": "600\r\n\t\t\t\t\t\t\t                1200"
                        },
                        "課後延托費": {
                            "收費期間": "月",
                            "單價": "1500",
                            "小計": "9000"
                        },
                        "家長會費": {
                            "收費期間": "",
                            "單價": "",
                            "小計": ""
                        }
                    }
                }
            },
            "下學期": {
                "months": "6",
                "class": {
                    "半日班": {
                        "學費": {
                            "收費期間": "學期",
                            "單價": "",
                            "小計": ""
                        },
                        "雜費": {
                            "收費期間": "月",
                            "單價": "",
                            "小計": ""
                        },
                        "材料費": {
                            "收費期間": "月",
                            "單價": "",
                            "小計": ""
                        },
                        "活動費": {
                            "收費期間": "月",
                            "單價": "",
                            "小計": ""
                        },
                        "午餐費": {
                            "收費期間": "月",
                            "單價": "",
                            "小計": ""
                        },
                        "點心費": {
                            "收費期間": "月",
                            "單價": "",
                            "小計": ""
                        },
                        "全學期總收費": {
                            "收費期間": "學期",
                            "單價": "",
                            "小計": ""
                        },
                        "交通費": {
                            "收費期間": "單趟\r\n                                                    雙趟",
                            "單價": "",
                            "小計": ""
                        },
                        "課後延托費": {
                            "收費期間": "月",
                            "單價": "",
                            "小計": ""
                        },
                        "家長會費": {
                            "收費期間": "",
                            "單價": "",
                            "小計": ""
                        }
                    },
                    "全日班": {
                        "學費": {
                            "收費期間": "學期",
                            "單價": "15000",
                            "小計": "15000"
                        },
                        "雜費": {
                            "收費期間": "月",
                            "單價": "1690",
                            "小計": "10140"
                        },
                        "材料費": {
                            "收費期間": "月",
                            "單價": "2800",
                            "小計": "16800"
                        },
                        "活動費": {
                            "收費期間": "月",
                            "單價": "2000",
                            "小計": "12000"
                        },
                        "午餐費": {
                            "收費期間": "月",
                            "單價": "1000",
                            "小計": "6000"
                        },
                        "點心費": {
                            "收費期間": "月",
                            "單價": "1200",
                            "小計": "7200"
                        },
                        "全學期總收費": {
                            "收費期間": "學期",
                            "單價": "67140",
                            "小計": "67140"
                        },
                        "交通費": {
                            "收費期間": "單趟\r\n                                                    雙趟",
                            "單價": "單\r\n\t\t\t\t\t\t\t                600\r\n\t\t\t\t\t\t\t                雙\r\n\t\t\t\t\t\t\t                1200",
                            "小計": "600\r\n\t\t\t\t\t\t\t                1200"
                        },
                        "課後延托費": {
                            "收費期間": "月",
                            "單價": "1500",
                            "小計": "9000"
                        },
                        "家長會費": {
                            "收費期間": "",
                            "單價": "",
                            "小計": ""
                        }
                    }
                }
            }
        }
    }
}